journal_vetter-1.0.1.dist-info/licenses/LICENSE
journalvetter/__init__.py
journalvetter/cli.py
journalvetter/config.py
journalvetter/core.py
journal_vetter-1.0.1.dist-info/METADATA
journal_vetter-1.0.1.dist-info/WHEEL
journal_vetter-1.0.1.dist-info/entry_points.txt
journal_vetter-1.0.1.dist-info/top_level.txt
journal_vetter-1.0.1.dist-info/RECORD
