Metadata-Version: 2.4
Name: journal-vetter
Version: 1.0.1
Summary: uses tokenized & carefully summarized journals to query an LLM for analysis, based also on user-defined YAML attributes
Author-email: Melina Norton <linamelina0707@gmail.com>
License: MIT
Project-URL: Homepage, https://github.com/MelinaNorton/journal-vetter
Project-URL: Documentation, https://github.com/MelinaNorton/journal-vetter#readme
Requires-Python: >=3.7
License-File: LICENSE
Requires-Dist: click>=8.0.0
Requires-Dist: langchain>=0.0.153
Requires-Dist: PyMuPDF>=1.20.0
Requires-Dist: python-dotenv>=0.21.0
Requires-Dist: openai>=0.27.0
Dynamic: license-file
